bread_slice/__init__.py
bread_slice/__main__.py
bread_slice/bot.py
bread_slice-0.0.1rc0.dist-info/LICENSE
bread_slice-0.0.1rc0.dist-info/METADATA
bread_slice-0.0.1rc0.dist-info/WHEEL
bread_slice-0.0.1rc0.dist-info/top_level.txt
bread_slice-0.0.1rc0.dist-info/RECORD
